{
  "generated_at": "2026-04-18T07:55:09.196472",
  "amazon_tag": "roccozoom-20",
  "ai_mode": "groq",
  "config": {
    "adsense_id": "ca-pub-4267818870826080",
    "pinterest_url": "",
    "site_url": "https://roccozoom.com"
  },
  "products": [
    {
      "title": "Stegosaurus Large Realistic Dinosaur Figure",
      "price": "$16.99",
      "category": "Dinosaurs",
      "age_group": "3-5",
      "image_url": "https://images.unsplash.com/photo-1535083783855-aaab5f24c4de?q=80&w=600",
      "link": "https://www.amazon.com/s?k=stegosaurus+large+figure+safari&tag=roccozoom-20",
      "review_text": "Kids love realistic dinosaur details",
      "styling_tip": "Pair with dinosaur books",
      "ai_score": 90,
      "rating": "4.4",
      "review_count": "2123"
    },
    {
      "title": "Jurassic World Dinosaur Escape Playset",
      "price": "$64.99",
      "category": "Playsets",
      "age_group": "6-9",
      "image_url": "https://images.unsplash.com/photo-1596461404969-9ae021eca1f0?q=80&w=600",
      "link": "https://www.amazon.com/s?k=jurassic+world+dominion+playset&tag=roccozoom-20",
      "review_text": "Kids love the thrilling dinosaur adventures",
      "styling_tip": "Pair with dinosaur figures",
      "ai_score": 97,
      "rating": "4.5",
      "review_count": "1957"
    },
    {
      "title": "Dragon Fire Fantasy Creature Figure",
      "price": "$29.99",
      "category": "Fantasy",
      "age_group": "10+",
      "image_url": "https://images.unsplash.com/photo-1604514628550-37477afdf4e3?q=80&w=600",
      "link": "https://www.amazon.com/s?k=dragon+fantasy+figure+large&tag=roccozoom-20",
      "review_text": "Vibrant dragon figure sparks imagination",
      "styling_tip": "Pair with fantasy books",
      "ai_score": 97,
      "rating": "4.3",
      "review_count": "2161"
    },
    {
      "title": "Castle Adventure Playset with Knights",
      "price": "$44.99",
      "category": "Playsets",
      "age_group": "6-9",
      "image_url": "https://images.unsplash.com/photo-1575783970733-1aaedde1db74?q=80&w=600",
      "link": "https://www.amazon.com/s?k=castle+playset+kids+knights&tag=roccozoom-20",
      "review_text": "Kids love the interactive knights",
      "styling_tip": "Pair with action figures",
      "ai_score": 92,
      "rating": "4.6",
      "review_count": "800"
    },
    {
      "title": "Coding Robot for Kids STEM Learning",
      "price": "$54.99",
      "category": "Educational",
      "age_group": "6-9",
      "image_url": "https://images.unsplash.com/photo-1509062522246-3755977927d7?q=80&w=600",
      "link": "https://www.amazon.com/s?k=coding+robot+kids+stem&tag=roccozoom-20",
      "review_text": "Kids love coding robots for fun learning",
      "styling_tip": "Pair with coding books",
      "ai_score": 91,
      "rating": "4.6",
      "review_count": "828"
    },
    {
      "title": "Marvel Spider-Man Bend And Flex Action Figure",
      "price": "$9.99",
      "category": "Action Figures",
      "age_group": "6-9",
      "image_url": "https://images.unsplash.com/photo-1608889175123-8ee362201f81?q=80&w=600",
      "link": "https://www.amazon.com/s?k=spiderman+action+figure&tag=roccozoom-20",
      "review_text": "Kids love Spider-Man's flexible adventures",
      "styling_tip": "Pair with Marvel playsets",
      "ai_score": 98,
      "rating": "4.9",
      "review_count": "1966"
    },
    {
      "title": "Dinosaur Figures Set — 12 Realistic Dinos",
      "price": "$24.99",
      "category": "Dinosaurs",
      "age_group": "3-5",
      "image_url": "https://images.unsplash.com/photo-1619566636858-adf3ef46400b?q=80&w=600",
      "link": "https://www.amazon.com/s?k=realistic+dinosaur+figure+set+12+pack&tag=roccozoom-20",
      "review_text": "Kids love realistic dinosaurs",
      "styling_tip": "Pair with dinosaur books",
      "ai_score": 88,
      "rating": "4.9",
      "review_count": "2037"
    },
    {
      "title": "Velociraptor Dinosaur with Sound Effects",
      "price": "$49.99",
      "category": "Dinosaurs",
      "age_group": "6-9",
      "image_url": "https://images.unsplash.com/photo-1606921231106-f1083329a65c?q=80&w=600",
      "link": "https://www.amazon.com/s?k=velociraptor+dinosaur+sound+toy&tag=roccozoom-20",
      "review_text": "Kids love roaring dinos",
      "styling_tip": "Pair with dino books",
      "ai_score": 88,
      "rating": "4.4",
      "review_count": "924"
    },
    {
      "title": "National Geographic Dinosaur Dig Kit",
      "price": "$18.99",
      "category": "Educational",
      "age_group": "6-9",
      "image_url": "https://images.unsplash.com/photo-1503676260728-1c00da094a0b?q=80&w=600",
      "link": "https://www.amazon.com/s?k=national+geographic+dinosaur+dig+kit&tag=roccozoom-20",
      "review_text": "Kids love uncovering dinosaur bones",
      "styling_tip": "Use a small brush",
      "ai_score": 87,
      "rating": "4.7",
      "review_count": "1651"
    },
    {
      "title": "T-Rex Roaring Electronic Dinosaur Toy",
      "price": "$34.99",
      "category": "Dinosaurs",
      "age_group": "3-5",
      "image_url": "https://images.unsplash.com/photo-1584714268709-c3dd9c92b378?q=80&w=600",
      "link": "https://www.amazon.com/s?k=t-rex+roaring+electronic+dinosaur&tag=roccozoom-20",
      "review_text": "Kids love its roaring sound",
      "styling_tip": "Pair with blocks",
      "ai_score": 91,
      "rating": "4.9",
      "review_count": "1008"
    },
    {
      "title": "Dinosaur Eggs Surprise Excavation Kit",
      "price": "$19.99",
      "category": "Dinosaurs",
      "age_group": "6-9",
      "image_url": "https://images.unsplash.com/photo-1562155618-e1a8c9b399c3?q=80&w=600",
      "link": "https://www.amazon.com/s?k=dinosaur+egg+excavation+kit&tag=roccozoom-20",
      "review_text": "Kids love uncovering dinosaur toys",
      "styling_tip": "Use with sand for realism",
      "ai_score": 98,
      "rating": "4.7",
      "review_count": "577"
    },
    {
      "title": "LEGO City Police Station Building Set",
      "price": "$59.99",
      "category": "Playsets",
      "age_group": "6-9",
      "image_url": "https://images.unsplash.com/photo-1558618047-3c8c76ca7d13?q=80&w=600",
      "link": "https://www.amazon.com/s?k=lego+city+police+station&tag=roccozoom-20",
      "review_text": "Kids love building and policing",
      "styling_tip": "Pair with mini figures",
      "ai_score": 94,
      "rating": "4.7",
      "review_count": "250"
    },
    {
      "title": "Remote Control Monster Truck Off Road",
      "price": "$34.99",
      "category": "Vehicles",
      "age_group": "6-9",
      "image_url": "https://images.unsplash.com/photo-1563861826100-9cb868fdbe1c?q=80&w=600",
      "link": "https://www.amazon.com/s?k=remote+control+monster+truck+kids&tag=roccozoom-20",
      "review_text": "Kids love its speed and durability",
      "styling_tip": "Pair with batteries for gift",
      "ai_score": 92,
      "rating": "4.9",
      "review_count": "458"
    },
    {
      "title": "Safari Ltd Farm Animal Figure Set 20pc",
      "price": "$27.99",
      "category": "Animals",
      "age_group": "3-5",
      "image_url": "https://images.unsplash.com/photo-1474511320723-9a56873867b5?q=80&w=600",
      "link": "https://www.amazon.com/s?k=safari+farm+animal+figure+set&tag=roccozoom-20",
      "review_text": "Vibrant farm animals delight kids.",
      "styling_tip": "Pair with play mats.",
      "ai_score": 87,
      "rating": "4.7",
      "review_count": "510"
    },
    {
      "title": "Toddler Pull-Along Wooden Animal Toy",
      "price": "$15.99",
      "category": "Animals",
      "age_group": "1-3",
      "image_url": "https://images.unsplash.com/photo-1518791841217-8f162f1912da?q=80&w=600",
      "link": "https://www.amazon.com/s?k=toddler+pull+along+wooden+animal&tag=roccozoom-20",
      "review_text": "Adorable wooden toy promotes walking skills",
      "styling_tip": "Great gift for toddlers",
      "ai_score": 95,
      "rating": "4.8",
      "review_count": "1717"
    },
    {
      "title": "Marvel Avengers Titan Hero Series 4-Pack",
      "price": "$44.99",
      "category": "Action Figures",
      "age_group": "6-9",
      "image_url": "https://images.unsplash.com/photo-1601987077677-5346c463575a?q=80&w=600",
      "link": "https://www.amazon.com/s?k=marvel+avengers+titan+hero+figure&tag=roccozoom-20",
      "review_text": "Kids love iconic Avengers heroes",
      "styling_tip": "Pair with Marvel playsets",
      "ai_score": 93,
      "rating": "4.7",
      "review_count": "487"
    },
    {
      "title": "Batman Dark Knight Poseable Action Figure",
      "price": "$19.99",
      "category": "Action Figures",
      "age_group": "6-9",
      "image_url": "https://images.unsplash.com/photo-1611532736597-de2d4265fba3?q=80&w=600",
      "link": "https://www.amazon.com/s?k=batman+action+figure+kids&tag=roccozoom-20",
      "review_text": "Kids love Batman's poseable action",
      "styling_tip": "Pair with Gotham City playset",
      "ai_score": 98,
      "rating": "4.6",
      "review_count": "1937"
    },
    {
      "title": "Wild Animal Kingdom Figure Collection",
      "price": "$21.99",
      "category": "Animals",
      "age_group": "3-5",
      "image_url": "https://images.unsplash.com/photo-1564349683136-77e08dba1ef7?q=80&w=600",
      "link": "https://www.amazon.com/s?k=wild+animal+kingdom+figure+collection&tag=roccozoom-20",
      "review_text": "Vibrant figures delight kids instantly.",
      "styling_tip": "Pair with blocks",
      "ai_score": 87,
      "rating": "4.8",
      "review_count": "2014"
    }
  ],
  "blog": {
    "title": "Best Toys for 3 Year Olds — Complete Buying Guide",
    "meta_description": "Find top toys for 3 yr olds",
    "summary": "Best toys for 3 year olds Amazon",
    "content": "<h2>Introduction to the Best Toys for 3 Year Olds</h2>\n<p>Choosing the right toys for your 3-year-old can be a daunting task, especially with the numerous options available in the market. At this age, children are naturally curious and love to explore their surroundings, making playtime an essential part of their development. The best toys for 3 year olds amazon offers can help stimulate their imagination, improve their motor skills, and enhance their problem-solving abilities. In this article, we will guide you through the process of selecting the most suitable toys for your child, highlighting the key factors to consider and recommending some of the top products available on Amazon.</p>\n\n<h2>Key Factors to Consider When Buying Toys for 3 Year Olds</h2>\n<p>Before making a purchase, it's essential to consider a few factors to ensure that the toy is both fun and safe for your child. Some of the key factors to consider include:</p>\n<ul>\n<li><strong>Safety</strong>: The toy should be made from non-toxic materials and have no small parts that can be a choking hazard.</li>\n<li><strong>Age appropriateness</strong>: The toy should be designed for 3-year-olds, taking into account their developmental stage and abilities.</li>\n<li><strong>Durability</strong>: The toy should be sturdy and able to withstand rough handling.</li>\n<li><strong>Engagement</strong>: The toy should be engaging and interactive, encouraging your child to play and learn.</li>\n</ul>\n\n<h2>Best Toys for 3 Year Olds Amazon Recommendations</h2>\n<p>Based on customer reviews and ratings, here are three of the best toys for 3 year olds amazon has to offer:</p>\n<p>The first recommendation is the <strong>Mega Bloks Big Building Bag</strong>, which is an excellent toy for developing fine motor skills and encouraging creativity. This set includes 60 pieces of blocks in different shapes and colors, allowing your child to build and create anything they can imagine.</p>\n<p>The second recommendation is the <strong>Fisher-Price Little People Farm</strong>, which is an interactive toy that teaches your child about farm animals and their sounds. This set includes a farm house, tractor, and several animal figures, making it an excellent choice for role-playing and imaginative play.</p>\n<p>The third recommendation is the <strong>Crayola Washable Markers</strong>, which is a set of vibrant and washable markers perfect for little artists. This set includes 10 different colors, allowing your child to express their creativity and bring their imagination to life.</p>\n\n<h2>Conclusion</h2>\n<p>In conclusion, choosing the best toys for 3 year olds amazon offers can be a challenging task, but by considering the key factors and reading customer reviews, you can make an informed decision. The Mega Bloks Big Building Bag, Fisher-Price Little People Farm, and Crayola Washable Markers are all excellent choices that can provide hours of entertainment and learning for your child. Remember to always prioritize your child's safety and age appropriateness when selecting toys, and don't hesitate to reach out to the manufacturer if you have any questions or concerns.</p>\n<p>By investing in the right toys, you can help your child develop their cognitive, emotional, and physical skills, setting them up for success in the future. So, start shopping for the best toys for 3 year olds amazon has to offer, and watch your child thrive and grow with the power of play.</p>",
    "image_url": "https://images.unsplash.com/photo-1558618666-fcd25c85cd64?q=80&w=800",
    "slug": "best-toys-for-3-year-olds-amazon"
  },
  "stats": {
    "total_products": 18,
    "categories": [
      "Animals",
      "Action Figures",
      "Playsets",
      "Vehicles",
      "Educational",
      "Dinosaurs",
      "Fantasy"
    ]
  }
}